gonk/__init__.py
gonk/apps.py
gonk/beat.py
gonk/contrib/__init__.py
gonk/contrib/expiration/__init__.py
gonk/contrib/expiration/mixins.py
gonk/contrib/notifications/__init__.py
gonk/contrib/notifications/mercure.py
gonk/contrib/notifications/settings.py
gonk/contrib/persistance/__init__.py
gonk/contrib/persistance/beat.py
gonk/contrib/rest_framework/__init__.py
gonk/contrib/rest_framework/exceptions.py
gonk/contrib/rest_framework/permissions.py
gonk/contrib/rest_framework/serializers.py
gonk/contrib/rest_framework/urls.py
gonk/contrib/rest_framework/viewsets.py
gonk/decorators.py
gonk/exceptions.py
gonk/management/__init__.py
gonk/management/commands/__init__.py
gonk/management/commands/create_task.py
gonk/management/commands/list_taskrunners.py
gonk/migrations/0001_initial.py
gonk/migrations/0002_auto_20220926_1514.py
gonk/migrations/0003_alter_task_retry_time.py
gonk/migrations/0004_task_with_warnings.py
gonk/migrations/__init__.py
gonk/models.py
gonk/registry.py
gonk/settings.py
gonk/taskrunners.py
gonk/tasks.py
gonk-0.6.1.dist-info/LICENSE
gonk-0.6.1.dist-info/METADATA
gonk-0.6.1.dist-info/WHEEL
gonk-0.6.1.dist-info/RECORD
