Metadata-Version: 2.1
Name: gonk
Version: 0.6.1
Summary: Celery tasks for Django made easy
Home-page: https://github.com/kasfactory/gonk
License: BSD-3-Clause
Keywords: celery,tasks
Author: Francisco Javier Lendinez Tirado
Author-email: lendinez@kasfactory.net
Requires-Python: >=3.9,<4.0
Classifier: Development Status :: 5 - Production/Stable
Classifier: Framework :: Django :: 3.2
Classifier: License :: OSI Approved :: BSD License
Classifier: Programming Language :: Python :: 3
Classifier: Programming Language :: Python :: 3.9
Classifier: Programming Language :: Python :: 3.10
Classifier: Programming Language :: Python :: 3.11
Classifier: Programming Language :: Python :: 3.10
Classifier: Programming Language :: Python :: 3.11
Classifier: Programming Language :: Python :: 3.8
Classifier: Programming Language :: Python :: 3.9
Classifier: Topic :: Software Development :: Libraries :: Python Modules
Provides-Extra: drf
Provides-Extra: mercure
Provides-Extra: persistance
Requires-Dist: Django (>=3.2.18)
Requires-Dist: PyJWT (>=1.5,<3.0) ; extra == "mercure"
Requires-Dist: celery (>=5.0.0,<6.0.0)
Requires-Dist: django-celery-beat (>=2.3.0,<3.0.0) ; extra == "persistance"
Requires-Dist: djangorestframework (>=3.0.0,<4.0.0) ; extra == "drf"
Requires-Dist: python-dateutil (>=2.8.2,<3.0.0)
Requires-Dist: requests (>=2.0.0,<3.0.0) ; extra == "mercure"
